rfc2html.py
rfc2html-2.0.2.dist-info/LICENSE
rfc2html-2.0.2.dist-info/METADATA
rfc2html-2.0.2.dist-info/WHEEL
rfc2html-2.0.2.dist-info/top_level.txt
rfc2html-2.0.2.dist-info/RECORD
