Metadata-Version: 2.1
Name: rfc2html
Version: 2.0.2
Summary: Convert text-format RFCs and Internet-Drafts to html
Home-page: https://github.com/ietf-tools/rfc2html/
Author: Henrik Levkowetz
Author-email: henrik@levkowetz.com
License: Simplified BSD
Keywords: RFC and Internet-Draft text to html conversion
Platform: UNKNOWN
Classifier: Development Status :: 5 - Production/Stable
Classifier: Intended Audience :: Other Audience
Classifier: Topic :: Text Processing
Classifier: Topic :: Text Processing :: Markup :: XML
Classifier: License :: OSI Approved :: BSD License
Classifier: Programming Language :: Python :: 2
Classifier: Programming Language :: Python :: 2.7
Classifier: Programming Language :: Python :: 3
Classifier: Programming Language :: Python :: 3.6
Classifier: Programming Language :: Python :: 3.7
Classifier: Programming Language :: Python :: 3.8
Classifier: Programming Language :: Python :: 3.9
License-File: LICENSE
Provides-Extra: dev
Requires-Dist: twine ; extra == 'dev'
